landlab_rest
