Metadata-Version: 1.1
Name: landlab-rest
Version: 0.2.0
Summary: A RESTful interface to landlab graphs.
Home-page: UNKNOWN
Author: Eric Hutton
Author-email: eric.hutton@colorado.edu
License: UNKNOWN
Platform: UNKNOWN
Classifier: Intended Audience :: Science/Research
Classifier: License :: OSI Approved :: MIT License
Classifier: Operating System :: OS Independent
Classifier: Programming Language :: Cython
Classifier: Programming Language :: Python :: 3
Classifier: Programming Language :: Python :: 3.6
Classifier: Programming Language :: Python :: 3.7
Classifier: Programming Language :: Python :: Implementation :: CPython
Classifier: Topic :: Scientific/Engineering :: Physics
